bqtools/__init__.py
bqtools/bqsync.py
bqtools/templates/bqschema.in
bqtools_json-1.0.10.dist-info/licenses/LICENSE
bqtools_json-1.0.10.dist-info/METADATA
bqtools_json-1.0.10.dist-info/WHEEL
bqtools_json-1.0.10.dist-info/entry_points.txt
bqtools_json-1.0.10.dist-info/top_level.txt
bqtools_json-1.0.10.dist-info/RECORD
