Metadata-Version: 2.4
Name: bqtools-json
Version: 1.0.10
Summary: A Big Query json utility package
Author-email: HSBC <opensource@hsbc.com>
Maintainer-email: HSBC <opensource@hsbc.com>
License-Expression: Apache-2.0
Project-URL: Homepage, https://github.com/hsbc/bqtools
Project-URL: Bug Reports, https://github.com/hsbc/bqtools/issues
Project-URL: Source, https://github.com/hsbc/bqtools/
Keywords: bqtools
Classifier: Development Status :: 3 - Alpha
Classifier: Intended Audience :: Developers
Classifier: Topic :: Software Development :: Build Tools
Classifier: Programming Language :: Python :: 3
Classifier: Programming Language :: Python :: 3.9
Classifier: Programming Language :: Python :: 3.10
Classifier: Programming Language :: Python :: 3.11
Classifier: Programming Language :: Python :: 3.12
Classifier: Programming Language :: Python :: 3.13
Classifier: Programming Language :: Python :: 3.14
Classifier: Programming Language :: Python :: 3 :: Only
Classifier: Operating System :: OS Independent
Requires-Python: >3.8
License-File: LICENSE
Requires-Dist: jinja2<4.0,>=2.0
Requires-Dist: google-cloud<1.0
Requires-Dist: google-cloud-bigquery<4.0,>=2.6.0
Requires-Dist: google-cloud-storage<4.0,>=1.0.0
Requires-Dist: google-cloud-logging<4.0,>=3.0
Requires-Dist: absl-py<3,>=1
Requires-Dist: google-api-python-client<3.0,>=2.0.0
Requires-Dist: grpcio~=1.0
Provides-Extra: dev
Requires-Dist: check-manifest; extra == "dev"
Requires-Dist: black; extra == "dev"
Provides-Extra: test
Requires-Dist: coverage; extra == "test"
Dynamic: license-file
